veyra/__init__.py
veyra/cli.py
veyra/interpreter.py
veyra/lexer.py
veyra/parser.py
veyra/pm.py
veyra/lib/math.veyra
veyra-0.2.0.dist-info/LICENSE
veyra-0.2.0.dist-info/METADATA
veyra-0.2.0.dist-info/WHEEL
veyra-0.2.0.dist-info/entry_points.txt
veyra-0.2.0.dist-info/top_level.txt
veyra-0.2.0.dist-info/RECORD
